polylatlib/__init__.py
polylatlib/classes/__init__.py
polylatlib/classes/base_shapes.py
polylatlib/classes/nonregular.py
polylatlib/classes/regular.py
polylatlib/exception.py
polylatlib/functions.py
polylatlib-1.0.3.dist-info/LICENSE
polylatlib-1.0.3.dist-info/METADATA
polylatlib-1.0.3.dist-info/WHEEL
polylatlib-1.0.3.dist-info/RECORD
