Metadata-Version: 2.1
Name: polylatlib
Version: 1.0.3
Summary: Python library providing the functionality to generate, work with, view, and manipulate polygons and their lattices in the 2D space.
Home-page: https://github.com/rexgreenway/polylatlib
License: GPL-3.0-or-later
Author: Rex Greenway
Author-email: rexgreenway@proton.me
Requires-Python: >=3.9,<4.0
Classifier: License :: OSI Approved :: GNU General Public License v3 or later (GPLv3+)
Classifier: Programming Language :: Python :: 3
Classifier: Programming Language :: Python :: 3.9
Classifier: Programming Language :: Python :: 3.10
Classifier: Programming Language :: Python :: 3.11
Classifier: Programming Language :: Python :: 3.12
Requires-Dist: matplotlib (>=3.8.2,<4.0.0)
Project-URL: Repository, https://github.com/rexgreenway/polylatlib
